nester2023.py
nester2023-1.1.0.dist-info/METADATA
nester2023-1.1.0.dist-info/WHEEL
nester2023-1.1.0.dist-info/top_level.txt
nester2023-1.1.0.dist-info/RECORD
