Metadata-Version: 2.1
Name: nester2023
Version: 1.1.0
Summary: A simple printer of nested lists
Home-page: 
Author: SM
Author-email: sonalimetkar1@gmail.com
